sarufi/__init__.py
sarufi-0.1.9.dist-info/LICENSE
sarufi-0.1.9.dist-info/METADATA
sarufi-0.1.9.dist-info/WHEEL
sarufi-0.1.9.dist-info/top_level.txt
sarufi-0.1.9.dist-info/RECORD
