Metadata-Version: 2.1
Name: sarufi
Version: 0.1.9
Summary: Opensource python wrapper to Sarufi Conversation API
Home-page: https://github.com/Neurotech-HQ/sarufi-python-sdk
Download-URL: https://github.com/Neurotech-HQ/sarufi-python-sdk/archive/refs/tags/v0.0.2.tar.gz
Author: Jordan Kalebu
Author-email: isaackeinstein@gmail.com
License: MIT
Keywords: sarufi,Sarufi Python SDK,Conversation API python,Swahili Conversational API,Conversational platform Python
Classifier: Development Status :: 3 - Alpha
Classifier: Intended Audience :: Developers
Classifier: Topic :: Software Development :: Build Tools
Classifier: License :: OSI Approved :: MIT License
Classifier: Programming Language :: Python :: 3.6
Classifier: Programming Language :: Python :: 3.7
Classifier: Programming Language :: Python :: 3.8
Classifier: Programming Language :: Python :: 3.9
Classifier: Programming Language :: Python :: 3.10
Requires-Python: >=3.6
License-File: LICENSE
Requires-Dist: requests
Requires-Dist: pyyaml
